breseq_ext_cnv/__init__.py
breseq_ext_cnv/get_CNV.py
breseq_ext_cnv-0.0.4.dist-info/LICENSE
breseq_ext_cnv-0.0.4.dist-info/METADATA
breseq_ext_cnv-0.0.4.dist-info/WHEEL
breseq_ext_cnv-0.0.4.dist-info/entry_points.txt
breseq_ext_cnv-0.0.4.dist-info/top_level.txt
breseq_ext_cnv-0.0.4.dist-info/RECORD
