Metadata-Version: 2.1
Name: breseq-ext-cnv
Version: 0.0.4
Summary: An extension of breseq to determine copy number variations from coverage data
Author-email: Pranesh Rao <pranesh.rao@utexas.edu>, Jefferey Barrick <jbarrick@utexas.edu>
Classifier: Programming Language :: Python :: 3
Classifier: License :: OSI Approved :: MIT License
Classifier: Operating System :: OS Independent
Requires-Python: >=3.9
License-File: LICENSE
Requires-Dist: pandas >=2.2.0
Requires-Dist: numpy >=1.26.0
Requires-Dist: matplotlib >=3.8.0
Requires-Dist: statsmodels >=0.14.0
Requires-Dist: scipy >=1.12.0
Requires-Dist: seaborn >=0.13.0
Requires-Dist: pathlib >=1.0.0
Requires-Dist: setuptools >=68.2.0
